textual_capture-0.3.0.dist-info/METADATA
textual_capture-0.3.0.dist-info/WHEEL
textual_capture-0.3.0.dist-info/entry_points.txt
textual_capture-0.3.0.dist-info/licenses/LICENSE
textual_capture/__init__.py
textual_capture/capture.py
textual_capture-0.3.0.dist-info/RECORD
