Metadata-Version: 2.1
Name: textual-capture
Version: 0.3.0
Summary: Sequenced screen capture for Textual TUI applications. Enables AI assistants to review and test TUIs.
Keywords: textual,tui,terminal,screenshot,screen capture,developer-tools,ai,llm,ai-tools,automated-testing,testing,automation,claude-code
Author-Email: eyecantell <paul@pneuma.solutions>
License: MIT
Classifier: Development Status :: 4 - Beta
Classifier: Environment :: Console
Classifier: Intended Audience :: Developers
Classifier: License :: OSI Approved :: MIT License
Classifier: Operating System :: OS Independent
Classifier: Programming Language :: Python :: 3
Classifier: Programming Language :: Python :: 3.9
Classifier: Programming Language :: Python :: 3.10
Classifier: Programming Language :: Python :: 3.11
Classifier: Programming Language :: Python :: 3.12
Classifier: Topic :: Software Development :: Libraries :: Python Modules
Classifier: Topic :: Terminals
Classifier: Topic :: Software Development :: User Interfaces
Project-URL: Homepage, https://github.com/eyecantell/textual-capture
Project-URL: Repository, https://github.com/eyecantell/textual-capture
Project-URL: Issues, https://github.com/eyecantell/textual-capture/issues
Project-URL: Documentation, https://github.com/eyecantell/textual-capture#readme
Project-URL: Changelog, https://github.com/eyecantell/textual-capture/releases
Requires-Python: >=3.9
Requires-Dist: textual>=6.11.0
Requires-Dist: tomli>=2.0.0; python_version < "3.11"
